app/__init__.py
app/__main__.py
app/cleaning.py
app/cli.py
app/column_mapper.py
app/fix_ref_file.py
app/main_logger.py
app/merge_csv.py
app/rename_files.py
app/subject_changer.py
app/timestamp_estimator.py
app/config/columns__std_format.csv
app/config/logs.yaml
app/util/rough_estimate_std_files.py
nhp_prep-1.0.2.dist-info/METADATA
nhp_prep-1.0.2.dist-info/WHEEL
nhp_prep-1.0.2.dist-info/entry_points.txt
nhp_prep-1.0.2.dist-info/top_level.txt
nhp_prep-1.0.2.dist-info/RECORD
