Metadata-Version: 2.1
Name: nhp-prep
Version: 1.0.2
Summary: Pre-processing data tool for NHP Lab @ CMU
Home-page: https://caoslab.psy.cmu.edu:32443/monkeylab/preprocessing-scripts
Author: Hugo Angulo, Zijun Zhao
Author-email: hugoanda@andrew.cmu.edu, zijunzha@andrew.cmu.edu
License: MIT
Keywords: nhp-prep,caoslab,cmu,pre-processing
Classifier: Development Status :: 5 - Production/Stable
Classifier: Intended Audience :: Science/Research
Classifier: License :: OSI Approved :: MIT License
Classifier: Operating System :: OS Independent
Classifier: Programming Language :: Python :: 3.8
Requires-Python: >=3.8
Requires-Dist: click (>=8.1.3)
Requires-Dist: pandas (>=1.5.1)
Requires-Dist: pyyaml (>=6.0)
Requires-Dist: setuptools (>=57.4.0)
